pydantic3/__init__.py
pydantic3/__pack__.py
pydantic3/agents/README.md
pydantic3/agents/__init__.py
pydantic3/agents/core/__init__.py
pydantic3/agents/core/agent.py
pydantic3/agents/core/processor.py
pydantic3/agents/core/session.py
pydantic3/agents/examples/form_generator_test.py
pydantic3/agents/examples/form_wizard_interactive.py
pydantic3/agents/examples/form_wizard_test.py
pydantic3/agents/examples/interactive_form.py
pydantic3/agents/examples/saved/form_structure_en.json
pydantic3/agents/examples/saved/form_structure_ru.json
pydantic3/agents/examples/simple_interactive.py
pydantic3/agents/examples/startup_form.py
pydantic3/agents/helpers/__init__.py
pydantic3/agents/helpers/interactive_session/README.md
pydantic3/agents/helpers/interactive_session/base.py
pydantic3/agents/models/__init__.py
pydantic3/agents/models/analytics.py
pydantic3/agents/models/drf_serializer.py
pydantic3/agents/models/form.py
pydantic3/agents/providers/__init__.py
pydantic3/agents/providers/openrouter.py
pydantic3/agents/utils/__init__.py
pydantic3/agents/utils/helper.py
pydantic3/agents/utils/model_factory.py
pydantic3/agents/utils/text_sanitizer.py
pydantic3/agents/wizards/form/README.md
pydantic3/agents/wizards/form/__init__.py
pydantic3/agents/wizards/form/form_generator.py
pydantic3/agents/wizards/form/models.py
pydantic3/agents/wizards/form/settings.py
pydantic3/agents/wizards/form/wizard.py
pydantic3/client/__init__.py
pydantic3/client/exceptions.py
pydantic3/client/message_handler.py
pydantic3/client/pydantic_ai_client.py
pydantic3/client/usage/model_prices.py
pydantic3/client/usage/usage_info.py
pydantic3/utils/__init__.py
pydantic3/utils/cli.py
pydantic3/utils/logger.py
pydantic3/utils/logging_config.py
pydantic3/utils/version_control/check.py
pydantic3-1.0.13.dist-info/LICENSE
pydantic3-1.0.13.dist-info/METADATA
pydantic3-1.0.13.dist-info/WHEEL
pydantic3-1.0.13.dist-info/entry_points.txt
pydantic3-1.0.13.dist-info/RECORD
