Metadata-Version: 2.3
Name: pydantic3
Version: 1.0.13
Summary: A powerful AI framework with structured Pydantic responses, flexible LLM integration, and advanced agent capabilities
License: MIT
Keywords: ai,pydantic,llm,agents
Author: Reforms.ai
Author-email: hello@reforms.ai
Requires-Python: >=3.11,<4.0
Classifier: Development Status :: 4 - Beta
Classifier: Intended Audience :: Developers
Classifier: Intended Audience :: Information Technology
Classifier: Intended Audience :: Science/Research
Classifier: License :: OSI Approved :: MIT License
Classifier: Operating System :: OS Independent
Classifier: Programming Language :: Python :: 3
Classifier: Programming Language :: Python :: 3.11
Classifier: Programming Language :: Python :: 3.12
Classifier: Programming Language :: Python :: 3.13
Classifier: Programming Language :: Python :: 3.10
Classifier: Programming Language :: Python :: 3.7
Classifier: Programming Language :: Python :: 3.8
Classifier: Programming Language :: Python :: 3.9
Classifier: Topic :: Scientific/Engineering :: Artificial Intelligence
Classifier: Topic :: Software Development :: Libraries
Classifier: Topic :: Text Processing :: Linguistic
Provides-Extra: dev
Requires-Dist: aiohttp (>=3.11.14,<4.0.0)
Requires-Dist: beautifulsoup4
Requires-Dist: click (>=8.1.7,<9.0.0)
Requires-Dist: colorlog (>=6.7.0,<7.0.0)
Requires-Dist: datasette (>=0.65.1,<0.66.0)
Requires-Dist: drf-pydantic (>=2.7.0,<3.0.0)
Requires-Dist: json-schema-to-pydantic (>=0.2.2,<0.3.0)
Requires-Dist: loguru
Requires-Dist: nest_asyncio
Requires-Dist: peewee (>=3.17.0,<4.0.0)
Requires-Dist: polyfactory
Requires-Dist: psutil (>=5.9.8,<6.0.0)
Requires-Dist: pydantic-ai (==0.0.43)
Requires-Dist: python-dotenv (>=1.0.0,<2.0.0)
Requires-Dist: pyyaml (>=6.0.2,<7.0.0)
Requires-Dist: questionary (>=2.0.1,<3.0.0)
Requires-Dist: rich
Requires-Dist: semver (>=3.0.2,<4.0.0)
Requires-Dist: typing-extensions (>=4.10.0,<5.0.0)
Project-URL: Documentation, https://pydantic.reforms.ai/
Project-URL: Homepage, https://pydantic.reforms.ai/
Project-URL: Repository, https://github.com/markolofsen/pydantic3
